{
  "Robot 0": {
    "type": "AFV",
    "price": 1018.33,
    "range": 87,
    "camera": false
  },
  "Robot 1": {
    "type": "ASV",
    "price": 6389.13,
    "range": 97,
    "camera": false
  },
  "Robot 2": {
    "type": "AGV",
    "price": 6556.76,
    "range": 26,
    "camera": false
  },
  "Robot 3": {
    "type": "ASV",
    "price": 6571.81,
    "range": 49,
    "camera": false
  },
  "Robot 4": {
    "type": "AGV",
    "price": 9916.45,
    "range": 74,
    "camera": false
  },
  "Robot 5": {
    "type": "AUV",
    "price": 9137.62,
    "range": 23,
    "camera": false
  },
  "Robot 6": {
    "type": "AGV",
    "price": 5349.77,
    "range": 79,
    "camera": true
  },
  "Robot 7": {
    "type": "AGV",
    "price": 8087.83,
    "range": 83,
    "camera": true
  },
  "Robot 8": {
    "type": "AUV",
    "price": 6622.7,
    "range": 83,
    "camera": true
  },
  "Robot 9": {
    "type": "AGV",
    "price": 28.93,
    "range": 47,
    "camera": false
  }
}